sentinel_downloader/__init__.py
sentinel_downloader/cli.py
sentinel_downloader/error_handler.py
sentinel_downloader/image_processing.py
sentinel_downloader/json_runner.py
sentinel_downloader/sentinel.py
sentinel_downloader/sentinel1.py
sentinel_downloader/sentinel2.py
sentinel_downloader/sentinel_downloader.py
sentinel_downloader/utils.py
sentinel_downloader/evalscripts/cloud.js
sentinel_downloader/evalscripts/rgb.js
sentinel_downloader/evalscripts/urban.js
sentinel_downloader/evalscripts/vegetation.js
sentinel_downloader/evalscripts/water.js
sentinel_downloader-2.0.1.dist-info/LICENSE
sentinel_downloader-2.0.1.dist-info/METADATA
sentinel_downloader-2.0.1.dist-info/WHEEL
sentinel_downloader-2.0.1.dist-info/entry_points.txt
sentinel_downloader-2.0.1.dist-info/top_level.txt
sentinel_downloader-2.0.1.dist-info/RECORD
