Metadata-Version: 2.1
Name: sentinel_downloader
Version: 2.0.1
Summary: A Python package for downloading and processing Sentinel satellite images.
Author-email: Pedro Vaz de Moraes Pertusi <pedrovazpertusi@gmail.com>, João Lucas de Moraes Cadorniga <joaolucasmbcadorniga@gmail.com>, Eduardo Mendes Vaz <emendesvaz@gmail.com>, Alexandre Magno Maciel dos Santos <alemagno03@gmail.com>
License: MIT
Project-URL: Homepage, https://github.com/JoaoLucasMBC/open-flood.git
Project-URL: Repository, https://github.com/JoaoLucasMBC/open-flood.git
Requires-Python: >=3.8
License-File: LICENSE
Requires-Dist: aenum
Requires-Dist: affine
Requires-Dist: attrs
Requires-Dist: bqplot
Requires-Dist: branca
Requires-Dist: cachetools
Requires-Dist: certifi
Requires-Dist: charset-normalizer
Requires-Dist: click
Requires-Dist: click-plugins
Requires-Dist: cligj
Requires-Dist: colour
Requires-Dist: comm
Requires-Dist: contourpy
Requires-Dist: cycler
Requires-Dist: dataclasses-json
Requires-Dist: decorator
Requires-Dist: earthengine-api
Requires-Dist: eerepr
Requires-Dist: exceptiongroup
Requires-Dist: executing
Requires-Dist: folium
Requires-Dist: fonttools
Requires-Dist: future
Requires-Dist: geemap
Requires-Dist: geocoder
Requires-Dist: google-api-core
Requires-Dist: google-api-python-client
Requires-Dist: google-auth
Requires-Dist: google-auth-httplib2
Requires-Dist: google-cloud-core
Requires-Dist: google-cloud-storage
Requires-Dist: google-crc32c
Requires-Dist: google-resumable-media
Requires-Dist: googleapis-common-protos
Requires-Dist: httplib2
Requires-Dist: idna
Requires-Dist: ipyevents
Requires-Dist: ipyfilechooser
Requires-Dist: ipyleaflet
Requires-Dist: ipython
Requires-Dist: ipytree
Requires-Dist: ipywidgets
Requires-Dist: jedi
Requires-Dist: Jinja2
Requires-Dist: jupyter-leaflet
Requires-Dist: jupyterlab-widgets
Requires-Dist: kiwisolver
Requires-Dist: MarkupSafe
Requires-Dist: marshmallow
Requires-Dist: matplotlib
Requires-Dist: matplotlib-inline
Requires-Dist: mypy-extensions
Requires-Dist: numpy
Requires-Dist: oauthlib
Requires-Dist: packaging
Requires-Dist: pandas
Requires-Dist: parso
Requires-Dist: pexpect
Requires-Dist: pillow
Requires-Dist: plotly
Requires-Dist: prompt-toolkit
Requires-Dist: proto-plus
Requires-Dist: protobuf
Requires-Dist: ptyprocess
Requires-Dist: pure-eval
Requires-Dist: pyasn1
Requires-Dist: pyasn1-modules
Requires-Dist: Pygments
Requires-Dist: pyparsing
Requires-Dist: pyperclip
Requires-Dist: pyproj
Requires-Dist: pyshp
Requires-Dist: python-box
Requires-Dist: python-dateutil
Requires-Dist: python-dotenv
Requires-Dist: pytz
Requires-Dist: rasterio
Requires-Dist: ratelim
Requires-Dist: requests
Requires-Dist: requests-oauthlib
Requires-Dist: rsa
Requires-Dist: scooby
Requires-Dist: sentinelhub
Requires-Dist: shapely
Requires-Dist: six
Requires-Dist: stack-data
Requires-Dist: tenacity
Requires-Dist: tifffile
Requires-Dist: tomli
Requires-Dist: tomli-w
Requires-Dist: tqdm
Requires-Dist: traitlets
Requires-Dist: traittypes
Requires-Dist: typing-inspect
Requires-Dist: typing-extensions
Requires-Dist: tzdata
Requires-Dist: uritemplate
Requires-Dist: urllib3
Requires-Dist: utm
Requires-Dist: wcwidth
Requires-Dist: widgetsnbextension
Requires-Dist: xyzservices
